cc_mapping/__init__.py
cc_mapping/core.py
cc_mapping/manifold.py
cc_mapping/plot.py
cc_mapping/preprocess.py
cc_mapping/pseudotime.py
cc_mapping/thresholding/__init__.py
cc_mapping/thresholding/base.py
cc_mapping/thresholding/sequential.py
cc_mapping/thresholding/single.py
cc_mapping/utils.py
cc_mapping/utils_v0.py
cc_mapping-0.1.1.dist-info/LICENSE
cc_mapping-0.1.1.dist-info/METADATA
cc_mapping-0.1.1.dist-info/WHEEL
cc_mapping-0.1.1.dist-info/RECORD
