Metadata-Version: 2.1
Name: cc-mapping
Version: 0.1.1
Summary: Gaussian Mixture Model-based thresholding for single-cell gene expression analysis
Home-page: https://github.com/StallaertLab/cc_mapping
License: MIT
Keywords: single-cell,gaussian-mixture-model,thresholding,gene-expression,cell-cycle,anndata,bioinformatics,computational-biology
Author: ddpoe
Author-email: dap182@pitt.edu
Requires-Python: >=3.10,<4.0
Classifier: Development Status :: 4 - Beta
Classifier: Intended Audience :: Science/Research
Classifier: License :: OSI Approved :: MIT License
Classifier: Programming Language :: Python :: 3
Classifier: Programming Language :: Python :: 3.10
Classifier: Programming Language :: Python :: 3.11
Classifier: Programming Language :: Python :: 3.12
Classifier: Topic :: Scientific/Engineering :: Bio-Informatics
Requires-Dist: anndata (>=0.10.0,<0.11.0)
Requires-Dist: kneed (>=0.8.5,<0.9.0)
Requires-Dist: matplotlib (>=3.7.0,<4.0.0)
Requires-Dist: mpl-scatter-density (>=0.8,<0.9)
Requires-Dist: numpy (>=1.24.0)
Requires-Dist: pandas (>=2.0.0,<3.0.0)
Requires-Dist: pydantic (>=2.10.0,<3.0.0)
Requires-Dist: scikit-learn (>=1.3.0,<2.0.0)
Requires-Dist: scipy (>=1.11.0,<2.0.0)
Project-URL: Documentation, https://cc-mapping.readthedocs.io
Project-URL: Repository, https://github.com/StallaertLab/cc_mapping
